trac_oidc-0.1.5.dist-info/WHEEL
trac_oidc-0.1.5.dist-info/pbr.json
trac_oidc-0.1.5.dist-info/top_level.txt
trac_oidc-0.1.5.dist-info/DESCRIPTION.rst
trac_oidc-0.1.5.dist-info/metadata.json
trac_oidc-0.1.5.dist-info/METADATA
trac_oidc-0.1.5.dist-info/entry_points.txt
trac_oidc-0.1.5.dist-info/zip-safe
trac_oidc-0.1.5.dist-info/RECORD
trac_oidc/util.py
trac_oidc/__init__.py
trac_oidc/authenticator.py
trac_oidc/api.py
trac_oidc/trac_oidc.py
trac_oidc/compat.py
trac_oidc/tests/test_functional.py
trac_oidc/tests/test_trac_oidc.py
trac_oidc/tests/__init__.py
trac_oidc/tests/test_util.py
trac_oidc/tests/test_authenticator.py
trac_oidc/tests/test_compat.py
