Metadata-Version: 2.0
Name: trac-oidc
Version: 0.1.5
Summary: OpenID Connect authentication for Trac
Home-page: https://github.com/trac-hacks/trac-oidc
Author: Jeff Dairiki
Author-email: dairiki@dairiki.org
License: Trac license (BSD-like)
Platform: UNKNOWN
Classifier: Development Status :: 4 - Beta
Classifier: Environment :: Plugins
Classifier: Environment :: Web Environment
Classifier: Framework :: Trac
Classifier: Intended Audience :: System Administrators
Classifier: Topic :: Internet :: WWW/HTTP
Classifier: Programming Language :: Python :: 2
Classifier: License :: OSI Approved :: BSD License
Requires-Dist: trac
Requires-Dist: oauth2client
Provides-Extra: testing
Requires-Dist: pytest; extra == 'testing'
Requires-Dist: pytest-capturelog; extra == 'testing'
Requires-Dist: Mock; extra == 'testing'
Requires-Dist: WebTest; extra == 'testing'
